odoo/addons/ssi_revenue_recognition/README.rst
odoo/addons/ssi_revenue_recognition/__init__.py
odoo/addons/ssi_revenue_recognition/__manifest__.py
odoo/addons/ssi_revenue_recognition/menu.xml
odoo/addons/ssi_revenue_recognition/data/account_journal_data.xml
odoo/addons/ssi_revenue_recognition/data/approval_template_data.xml
odoo/addons/ssi_revenue_recognition/data/base_automation_data.xml
odoo/addons/ssi_revenue_recognition/data/ir_actions_server_data.xml
odoo/addons/ssi_revenue_recognition/data/ir_sequence_data.xml
odoo/addons/ssi_revenue_recognition/data/policy_template_data.xml
odoo/addons/ssi_revenue_recognition/data/sequence_template_data.xml
odoo/addons/ssi_revenue_recognition/demo/account_account_demo.xml
odoo/addons/ssi_revenue_recognition/demo/account_journal_demo.xml
odoo/addons/ssi_revenue_recognition/demo/product_usage_type_demo.xml
odoo/addons/ssi_revenue_recognition/demo/revenue_recognition_type_demo.xml
odoo/addons/ssi_revenue_recognition/models/__init__.py
odoo/addons/ssi_revenue_recognition/models/account_analytic_account.py
odoo/addons/ssi_revenue_recognition/models/performance_obligation_acceptance.py
odoo/addons/ssi_revenue_recognition/models/performance_obligation_acceptance_manual_fulfillment.py
odoo/addons/ssi_revenue_recognition/models/revenue_recognition.py
odoo/addons/ssi_revenue_recognition/models/revenue_recognition_account.py
odoo/addons/ssi_revenue_recognition/models/revenue_recognition_type.py
odoo/addons/ssi_revenue_recognition/models/revenue_recognition_type_account.py
odoo/addons/ssi_revenue_recognition/models/service_contract.py
odoo/addons/ssi_revenue_recognition/models/service_contract_fix_item.py
odoo/addons/ssi_revenue_recognition/models/service_contract_performance_obligation.py
odoo/addons/ssi_revenue_recognition/models/service_type.py
odoo/addons/ssi_revenue_recognition/security/ir.model.access.csv
odoo/addons/ssi_revenue_recognition/security/ir_module_category_data.xml
odoo14_addon_ssi_revenue_recognition-14.0.4.7.0.dist-info/METADATA
odoo14_addon_ssi_revenue_recognition-14.0.4.7.0.dist-info/WHEEL
odoo14_addon_ssi_revenue_recognition-14.0.4.7.0.dist-info/top_level.txt
odoo14_addon_ssi_revenue_recognition-14.0.4.7.0.dist-info/RECORD
